fastapi_cache_plus/__init__.py
fastapi_cache_plus/py.typed
fastapi_cache_plus/registry.py
fastapi_cache_plus/backends/__init__.py
fastapi_cache_plus/backends/base.py
fastapi_cache_plus/backends/memory.py
fastapi_cache_plus/backends/redis.py
fastapi_cache_plus/backends/utils/__init__.py
fastapi_cache_plus/backends/utils/ttldict.py
fastapi_cache_plus-0.2.0.dist-info/METADATA
fastapi_cache_plus-0.2.0.dist-info/WHEEL
fastapi_cache_plus-0.2.0.dist-info/RECORD
