Metadata-Version: 2.4
Name: fastapi-cache-plus
Version: 0.2.0
Summary: FastAPI simple cache
Project-URL: Homepage, https://github.com/leynier/fastapi-cache-plus
Project-URL: Repository, https://github.com/leynier/fastapi-cache-plus
Project-URL: Issues, https://github.com/leynier/fastapi-cache-plus/issues
Project-URL: Changelog, https://github.com/leynier/fastapi-cache-plus/blob/master/changelog.md
Author-email: Leynier Gutiérrez González <leynier41@gmail.com>
License-Expression: MIT
Keywords: aioredis,asyncio,cache,fastapi,redis,starlette
Classifier: Development Status :: 4 - Beta
Classifier: Framework :: FastAPI
Classifier: Intended Audience :: Developers
Classifier: License :: OSI Approved :: MIT License
Classifier: Programming Language :: Python
Classifier: Programming Language :: Python :: 3
Classifier: Programming Language :: Python :: 3.6
Classifier: Programming Language :: Python :: 3.7
Classifier: Programming Language :: Python :: 3.8
Classifier: Programming Language :: Python :: 3.9
Classifier: Programming Language :: Python :: 3.10
Classifier: Programming Language :: Python :: 3.11
Classifier: Programming Language :: Python :: 3.12
Classifier: Programming Language :: Python :: 3.13
Classifier: Topic :: Software Development :: Libraries
Classifier: Topic :: Software Development :: Libraries :: Python Modules
Requires-Python: >=3.6
Requires-Dist: aioredis==1.3.1
